mortal_portrait/__init__.py
mortal_portrait/portrait_main.cpython-311-x86_64-linux-gnu.so
mortal_portrait-4.5.0.dist-info/METADATA
mortal_portrait-4.5.0.dist-info/WHEEL
mortal_portrait-4.5.0.dist-info/top_level.txt
mortal_portrait-4.5.0.dist-info/RECORD
